ml_board/__init__.py
ml_board/backend/__init__.py
ml_board/backend/error_handling/__init__.py
ml_board/backend/error_handling/exception.py
ml_board/backend/frontend_service/__init__.py
ml_board/backend/frontend_service/server.py
ml_board/backend/messaging/__init__.py
ml_board/backend/messaging/broker.py
ml_board/backend/messaging/event_storage.py
ml_board/backend/messaging/events.py
ml_board/backend/restful_api/__init__.py
ml_board/backend/restful_api/data_access.py
ml_board/backend/restful_api/data_models.py
ml_board/backend/restful_api/restful_api_server.py
ml_board/backend/starter_scripts/__init__.py
ml_board/backend/starter_scripts/ml_board
ml_board/backend/starter_scripts/ml_board_rest_endpoint
ml_board/backend/starter_scripts/ml_board_ws_endpoint
ml_board/backend/websocket_api/__init__.py
ml_board/backend/websocket_api/websocket_server.py
ml_board/backend/websocket_api/websocket_server_dummy.py
ml_board/frontend/dashboard/build/asset-manifest.json
ml_board/frontend/dashboard/build/favicon.ico
ml_board/frontend/dashboard/build/index.html
ml_board/frontend/dashboard/build/logo192.png
ml_board/frontend/dashboard/build/logo512.png
ml_board/frontend/dashboard/build/manifest.json
ml_board/frontend/dashboard/build/robots.txt
ml_board/frontend/dashboard/build/static/css/main.2a932ca7.css
ml_board/frontend/dashboard/build/static/css/main.2a932ca7.css.map
ml_board/frontend/dashboard/build/static/js/787.545aecf5.chunk.js
ml_board/frontend/dashboard/build/static/js/787.545aecf5.chunk.js.map
ml_board/frontend/dashboard/build/static/js/main.1cf42915.js
ml_board/frontend/dashboard/build/static/js/main.1cf42915.js.LICENSE.txt
ml_board/frontend/dashboard/build/static/js/main.1cf42915.js.map
ml_gym/__init__.py
ml_gym/modes.py
ml_gym/starter.py
ml_gym/batching/__init__.py
ml_gym/batching/batch.py
ml_gym/batching/batch_filters.py
ml_gym/blueprints/__init__.py
ml_gym/blueprints/blue_prints.py
ml_gym/blueprints/component_factory.py
ml_gym/blueprints/constructables.py
mlgym-0.0.75.dist-info/METADATA
mlgym-0.0.75.dist-info/WHEEL
mlgym-0.0.75.dist-info/top_level.txt
mlgym-0.0.75.dist-info/RECORD
