Metadata-Version: 2.1
Name: mlgym
Version: 0.0.75
Summary: MLgym, a python framework for distributeda and reproducible machine learning model training in research.
Home-page: https://github.com/mlgym/mlgym
Author: Max Luebbering
Requires-Python: >=3.7
Requires-Dist: pytest
Requires-Dist: pytest-cov
Requires-Dist: torch
Requires-Dist: h5py
Requires-Dist: tqdm
Requires-Dist: pyyaml
Requires-Dist: datastack
Requires-Dist: scipy
Requires-Dist: scikit-learn
Requires-Dist: python-socketio
Requires-Dist: fastapi
Requires-Dist: uvicorn
Requires-Dist: requests
Requires-Dist: python-multipart
Requires-Dist: flask
Requires-Dist: Flask-SocketIO
Requires-Dist: eventlet
Requires-Dist: python-socketio[client]
Requires-Dist: gunicorn
